slide_lsst/__init__.py
slide_lsst/_version.py
slide_lsst/image_processing.py
slide_lsst/lsst_utils.py
slide_lsst/reference_download.py
slide_lsst/slide_image_class.py
slide_lsst/subtraction.py
slide_lsst-0.2.0.dist-info/LICENSE.temp
slide_lsst-0.2.0.dist-info/METADATA
slide_lsst-0.2.0.dist-info/WHEEL
slide_lsst-0.2.0.dist-info/top_level.txt
slide_lsst-0.2.0.dist-info/RECORD
