Metadata-Version: 2.1
Name: slide-lsst
Version: 0.2.0
Summary: Image subtraction package for LSST using DECam templates
Author-email: Yize Dong <yize.dong@outlook.com>
Maintainer-email: Yize Dong <yize.dong@outlook.com>
Project-URL: Homepage, https://github.com/yizedong/SLIDE
Project-URL: Documentation, https://github.com/yizedong/SLIDE#readme
Project-URL: Repository, https://github.com/yizedong/SLIDE
Project-URL: Bug Tracker, https://github.com/yizedong/SLIDE/issues
Keywords: astronomy,lsst,decam,image-subtraction,transient-detection
Classifier: Development Status :: 4 - Beta
Classifier: Intended Audience :: Science/Research
Classifier: Operating System :: OS Independent
Classifier: Programming Language :: Python :: 3
Classifier: Programming Language :: Python :: 3.10
Classifier: Programming Language :: Python :: 3.11
Classifier: Programming Language :: Python :: 3.12
Classifier: Topic :: Scientific/Engineering :: Astronomy
Classifier: Topic :: Scientific/Engineering :: Physics
Requires-Python: >=3.10
License-File: LICENSE.temp
Requires-Dist: numpy >=1.20.0
Requires-Dist: scipy >=1.7.0
Requires-Dist: matplotlib >=3.3.0
Requires-Dist: astropy >=5.0.0
Requires-Dist: photutils >=1.4.0
Requires-Dist: reproject >=0.8.0
Requires-Dist: sep >=1.1.0
Requires-Dist: requests >=2.25.0
Requires-Dist: pyvo >=1.3.0
Requires-Dist: astroquery >=0.4.6
Requires-Dist: psutil >=5.8.0
Provides-Extra: dev
Requires-Dist: pytest >=6.0 ; extra == 'dev'
Requires-Dist: pytest-cov >=2.0 ; extra == 'dev'
Requires-Dist: black >=21.0 ; extra == 'dev'
Requires-Dist: flake8 >=3.8 ; extra == 'dev'
Provides-Extra: docs
Requires-Dist: sphinx >=4.0 ; extra == 'docs'
Requires-Dist: sphinx-rtd-theme >=1.0 ; extra == 'docs'
